setup.py
libgfb/__init__.py
libgfb/libgfb.py
libgfb.egg-info/PKG-INFO
libgfb.egg-info/SOURCES.txt
libgfb.egg-info/dependency_links.txt
libgfb.egg-info/top_level.txt