Metadata-Version: 1.1
Name: libgfb
Version: 0.4.0
Summary: A library for reading and writing binary gene database files.
Home-page: https://github.com/antonybholmes/libgfb
Author: Antony B Holmes
Author-email: antony.b.holmes@gmail.com
License: UNKNOWN
Platform: UNKNOWN
Classifier: Programming Language :: Python :: 3
Classifier: License :: OSI Approved :: MIT License
Classifier: Operating System :: OS Independent
